AUTHORS.md
CHANGELOG.md
django_ufilter/__init__.py
django_ufilter/backends/__init__.py
django_ufilter/backends/base.py
django_ufilter/backends/django.py
django_ufilter/backends/plain.py
django_ufilter/constants.py
django_ufilter/exceptions.py
django_ufilter/fields.py
django_ufilter/filters.py
django_ufilter/filtersets/__init__.py
django_ufilter/filtersets/base.py
django_ufilter/filtersets/django.py
django_ufilter/filtersets/plain.py
django_ufilter/integrations/__init__.py
django_ufilter/integrations/drf.py
django_ufilter/utils.py
django_ufilter/validators.py
django_ufilter-0.4.3.dist-info/LICENSE.md
django_ufilter-0.4.3.dist-info/METADATA
django_ufilter-0.4.3.dist-info/WHEEL
django_ufilter-0.4.3.dist-info/RECORD
