Metadata-Version: 2.1
Name: django-ufilter
Version: 0.4.3
Summary: django-ufilter provides a safe way to filter data.
Home-page: https://github.com/Qu4tro/django-ufilter
License: MIT
Keywords: django,django-rest-framework
Author: Miroslav Shubernetskiy
Author-email: miroslav@miki725.com
Maintainer: Xavier Francisco
Maintainer-email: xavier.n.francisco@gmail.com
Requires-Python: >=3.7,<4.0
Classifier: Development Status :: 2 - Pre-Alpha
Classifier: Intended Audience :: Developers
Classifier: License :: OSI Approved :: MIT License
Classifier: Natural Language :: English
Classifier: Programming Language :: Python
Classifier: Programming Language :: Python :: 3
Classifier: Programming Language :: Python :: 3.7
Classifier: Programming Language :: Python :: 3.8
Classifier: Programming Language :: Python :: 3.9
Classifier: Programming Language :: Python :: 3.10
Classifier: Programming Language :: Python :: 3.11
Classifier: Programming Language :: Python :: 2.7
Classifier: Programming Language :: Python :: 3
Classifier: Programming Language :: Python :: 3.4
Requires-Dist: cached-property (>=1.5.2,<2.0.0)
Requires-Dist: django (>=3.2)
Project-URL: Repository, https://github.com/Qu4tro/django-ufilter
